{
  "url": "https://baseball.yahoo.co.jp/npb/game/2021040066/text",
  "title": "2026年3月11日 福岡ソフトバンクホークスvs.読売ジャイアンツ 試合テキスト速報 - プロ野球 - スポーツナビ",
  "updated_at": "2026/3/11 21:08",
  "scoreboard": [
    {
      "team": "巨人",
      "inning_scores": [
        "0",
        "1",
        "0",
        "1",
        "0",
        "0",
        "0",
        "0",
        "0"
      ],
      "R": "2",
      "H": "7",
      "E": "0"
    },
    {
      "team": "ソフトバンク",
      "inning_scores": [
        "5",
        "3",
        "2",
        "0",
        "0",
        "3",
        "0",
        "2",
        "X"
      ],
      "R": "15",
      "H": "12",
      "E": "0"
    }
  ],
  "text_live": [
    {
      "inning": "試合前情報",
      "detail": "",
      "plays": [
        {
          "number": "",
          "lines": [
            "先発ピッチャーはソフトバンクが 大津 、巨人が ウィットリー",
            "先攻:巨人のスターティングラインアップは1番: 佐々木 (中)、2番: 泉口 (遊)、3番: 坂本勇 (指)、4番: ダルベック (三)、5番: キャベッジ (左)、6番: 中山 (右)、7番: リチャード (一)、8番: 甲斐 (捕)、9番: 門脇 (二)",
            "後攻:ソフトバンクのスターティングラインアップは1番: 柳田 (左)、2番: 柳町 (右)、3番: 栗原 (三)、4番: 山川 (指)、5番: 笹川 (中)、6番: 今宮 (遊)、7番: 秋広 (一)、8番: 谷川原 (捕)、9番: 川瀬 (二)"
          ]
        }
      ],
      "pregame": {
        "raw_lines": [
          "先発ピッチャーはソフトバンクが 大津 、巨人が ウィットリー",
          "先攻:巨人のスターティングラインアップは1番: 佐々木 (中)、2番: 泉口 (遊)、3番: 坂本勇 (指)、4番: ダルベック (三)、5番: キャベッジ (左)、6番: 中山 (右)、7番: リチャード (一)、8番: 甲斐 (捕)、9番: 門脇 (二)",
          "後攻:ソフトバンクのスターティングラインアップは1番: 柳田 (左)、2番: 柳町 (右)、3番: 栗原 (三)、4番: 山川 (指)、5番: 笹川 (中)、6番: 今宮 (遊)、7番: 秋広 (一)、8番: 谷川原 (捕)、9番: 川瀬 (二)"
        ],
        "pitchers": [],
        "lineups": [
          {
            "side": "先攻",
            "players": [
              "佐々木",
              "泉口",
              "坂本勇",
              "ダルベック",
              "キャベッジ",
              "中山",
              "リチャード",
              "甲斐",
              "門脇"
            ],
            "text": "先攻:巨人のスターティングラインアップは1番: 佐々木 (中)、2番: 泉口 (遊)、3番: 坂本勇 (指)、4番: ダルベック (三)、5番: キャベッジ (左)、6番: 中山 (右)、7番: リチャード (一)、8番: 甲斐 (捕)、9番: 門脇 (二)"
          },
          {
            "side": "後攻",
            "players": [
              "柳田",
              "柳町",
              "栗原",
              "山川",
              "笹川",
              "今宮",
              "秋広",
              "谷川原",
              "川瀬"
            ],
            "text": "後攻:ソフトバンクのスターティングラインアップは1番: 柳田 (左)、2番: 柳町 (右)、3番: 栗原 (三)、4番: 山川 (指)、5番: 笹川 (中)、6番: 今宮 (遊)、7番: 秋広 (一)、8番: 谷川原 (捕)、9番: 川瀬 (二)"
          }
        ],
        "player_names": [
          "佐々木",
          "泉口",
          "坂本勇",
          "ダルベック",
          "キャベッジ",
          "中山",
          "リチャード",
          "甲斐",
          "門脇",
          "柳田",
          "柳町",
          "栗原",
          "山川",
          "笹川",
          "今宮",
          "秋広",
          "谷川原",
          "川瀬"
        ]
      }
    },
    {
      "inning": "1回表",
      "detail": "巨人の攻撃",
      "plays": [
        {
          "number": "1：",
          "lines": [
            "1番 佐々木 俊輔 無死走者なし",
            "外角低めの落ちる球を引っかけてセカンドゴロ 1アウト"
          ]
        },
        {
          "number": "2：",
          "lines": [
            "2番 泉口 友汰 一死走者なし",
            "レフトへのヒットで出塁 一塁"
          ]
        },
        {
          "number": "3：",
          "lines": [
            "3番 坂本 勇人 一死一塁",
            "見逃し三振でバッターアウト！ 2アウト"
          ]
        },
        {
          "number": "4：",
          "lines": [
            "4番 ダルベック 二死一塁",
            "一塁けん制:ランナー 泉口 帰塁",
            "見逃し三振 3アウト"
          ]
        }
      ]
    },
    {
      "inning": "1回裏",
      "detail": "ソフトバンクの攻撃",
      "plays": [
        {
          "number": "1：",
          "lines": [
            "1番 柳田 悠岐 無死走者なし",
            "フォアボールを選ぶ 一塁"
          ]
        },
        {
          "number": "2：",
          "lines": [
            "2番 柳町 達 無死一塁",
            "死球を受ける 一二塁"
          ]
        },
        {
          "number": "3：",
          "lines": [
            "3番 栗原 陵矢 無死一二塁",
            "ランナー一二塁から内角の球を打つもセンターフライ 1アウト二三塁"
          ]
        },
        {
          "number": "4：",
          "lines": [
            "4番 山川 穂高 一死二三塁",
            "1アウト二三塁の2-1からレフトへの先制タイムリーヒット！ ソ 1-0 巨 一三塁"
          ]
        },
        {
          "number": "5：",
          "lines": [
            "5番 笹川 吉康 一死一三塁",
            "デッドボールを受ける 満塁"
          ]
        },
        {
          "number": "6：",
          "lines": [
            "6番 今宮 健太 一死満塁",
            "－巨人:コーチマウンドへむかう－",
            "見逃し三振 2アウト"
          ]
        },
        {
          "number": "7：",
          "lines": [
            "7番 秋広 優人 二死満塁",
            "2アウト満塁の0-1から右中間への満塁ホームラン ソ 5-0 巨"
          ]
        },
        {
          "number": "8：",
          "lines": [
            "8番 谷川原 健太 二死走者なし",
            "ファウルフライを ダルベック (三)がつかんでバッターアウト 3アウト"
          ]
        }
      ]
    },
    {
      "inning": "2回表",
      "detail": "巨人の攻撃",
      "plays": [
        {
          "number": "1：",
          "lines": [
            "5番 キャベッジ 無死走者なし",
            "フェンス直撃の二塁打を放つ 二塁"
          ]
        },
        {
          "number": "2：",
          "lines": [
            "6番 中山 礼都 無死二塁",
            "ランナー二塁からライトへのヒットで出塁 一三塁"
          ]
        },
        {
          "number": "3：",
          "lines": [
            "7番 リチャード 無死一三塁",
            "デッドボールを受ける 満塁"
          ]
        },
        {
          "number": "4：",
          "lines": [
            "8番 甲斐 拓也 無死満塁",
            "0アウト満塁の1-2からダブルプレーの間に一人ランナーがかえり巨人1点をあげる ソ 5-1 巨 2アウト三塁"
          ]
        },
        {
          "number": "5：",
          "lines": [
            "9番 門脇 誠 二死三塁",
            "ランナー三塁からファーストゴロ 3アウト"
          ]
        }
      ]
    },
    {
      "inning": "2回裏",
      "detail": "ソフトバンクの攻撃",
      "plays": [
        {
          "number": "1：",
          "lines": [
            "9番 川瀬 晃 無死走者なし",
            "投手交代: ウィットリー → 松浦",
            "内角高めの真っ直ぐを打つもレフトフライ 1アウト"
          ]
        },
        {
          "number": "2：",
          "lines": [
            "1番 柳田 悠岐 一死走者なし",
            "ファウルフライを 泉口 (遊)が捕球してバッターアウト 2アウト"
          ]
        },
        {
          "number": "3：",
          "lines": [
            "2番 柳町 達 二死走者なし",
            "フォアボールを選ぶ 一塁"
          ]
        },
        {
          "number": "4：",
          "lines": [
            "3番 栗原 陵矢 二死一塁",
            "フォアボールを選ぶ 一二塁"
          ]
        },
        {
          "number": "5：",
          "lines": [
            "4番 山川 穂高 二死一二塁",
            "2アウト一二塁の3-2から右中間への3ランホームラン ソ 8-1 巨"
          ]
        },
        {
          "number": "6：",
          "lines": [
            "5番 笹川 吉康 二死走者なし",
            "ショートフライ 3アウト"
          ]
        }
      ]
    },
    {
      "inning": "3回表",
      "detail": "巨人の攻撃",
      "plays": [
        {
          "number": "1：",
          "lines": [
            "1番 佐々木 俊輔 無死走者なし",
            "ショートゴロ 1アウト"
          ]
        },
        {
          "number": "2：",
          "lines": [
            "2番 泉口 友汰 一死走者なし",
            "ファーストゴロ 2アウト"
          ]
        },
        {
          "number": "3：",
          "lines": [
            "3番 坂本 勇人 二死走者なし",
            "ショートゴロ 3アウト"
          ]
        }
      ]
    },
    {
      "inning": "3回裏",
      "detail": "ソフトバンクの攻撃",
      "plays": [
        {
          "number": "1：",
          "lines": [
            "6番 今宮 健太 無死走者なし",
            "投手交代: 松浦 → 田和",
            "空振りの三振を喫する 1アウト"
          ]
        },
        {
          "number": "2：",
          "lines": [
            "7番 秋広 優人 一死走者なし",
            "センターへのヒットで出塁 一塁"
          ]
        },
        {
          "number": "3：",
          "lines": [
            "8番 谷川原 健太 一死一塁",
            "死球を受ける 一二塁"
          ]
        },
        {
          "number": "4：",
          "lines": [
            "9番 川瀬 晃 一死一二塁",
            "1アウト一二塁の2-1からセンターへのタイムリーヒット ソ 9-1 巨 一三塁"
          ]
        },
        {
          "number": "5：",
          "lines": [
            "1番 柳田 悠岐 一死一三塁",
            "ファーストゴロの間にソフトバンク1点をあげる ソ 10-1 巨 2アウト二塁"
          ]
        },
        {
          "number": "6：",
          "lines": [
            "2番 柳町 達 二死二塁",
            "四球を選ぶ 一二塁"
          ]
        },
        {
          "number": "7：",
          "lines": [
            "3番 栗原 陵矢 二死一二塁",
            "セカンドゴロ 3アウト"
          ]
        }
      ]
    },
    {
      "inning": "4回表",
      "detail": "巨人の攻撃",
      "plays": [
        {
          "number": "1：",
          "lines": [
            "4番 ダルベック 無死走者なし",
            "フォアボールを選ぶ 一塁"
          ]
        },
        {
          "number": "2：",
          "lines": [
            "5番 キャベッジ 無死一塁",
            "セカンドゴロ 1アウト二塁"
          ]
        },
        {
          "number": "3：",
          "lines": [
            "6番 中山 礼都 一死二塁",
            "ランナー二塁の1-1からライトへのタイムリーヒット ソ 10-2 巨 一塁"
          ]
        },
        {
          "number": "4：",
          "lines": [
            "7番 リチャード 一死一塁",
            "一塁けん制:ランナー 中山 帰塁",
            "空振りの三振を喫する 2アウト"
          ]
        },
        {
          "number": "5：",
          "lines": [
            "8番 甲斐 拓也 二死一塁",
            "内角低めの球を打つもセンターフライ 3アウト"
          ]
        }
      ]
    },
    {
      "inning": "4回裏",
      "detail": "ソフトバンクの攻撃",
      "plays": [
        {
          "number": "1：",
          "lines": [
            "4番 山川 穂高 無死走者なし",
            "投手交代: 田和 → 戸郷 守備交代:セカンド 浦田 守備変更: ダルベック サード→ファースト　守備変更: 門脇 セカンド→サード",
            "四球を選ぶ 一塁"
          ]
        },
        {
          "number": "2：",
          "lines": [
            "5番 笹川 吉康 無死一塁",
            "併殺打 2アウト"
          ]
        },
        {
          "number": "3：",
          "lines": [
            "6番 今宮 健太 二死走者なし",
            "サードゴロ 3アウト"
          ]
        }
      ]
    },
    {
      "inning": "5回表",
      "detail": "巨人の攻撃",
      "plays": [
        {
          "number": "1：",
          "lines": [
            "9番 門脇 誠 無死走者なし",
            "守備交代:セカンド 野村 守備変更: 川瀬 セカンド→サード",
            "サードゴロ 1アウト"
          ]
        },
        {
          "number": "2：",
          "lines": [
            "1番 佐々木 俊輔 一死走者なし",
            "－ソフトバンク:コーチマウンドへむかう－",
            "投手交代: 大津 → 伊藤",
            "粘りを見せるも8球目を空振り、三振を喫する 2アウト"
          ]
        },
        {
          "number": "3：",
          "lines": [
            "2番 泉口 友汰 二死走者なし",
            "ショートゴロ 3アウト"
          ]
        }
      ]
    },
    {
      "inning": "5回裏",
      "detail": "ソフトバンクの攻撃",
      "plays": [
        {
          "number": "1：",
          "lines": [
            "7番 秋広 優人 無死走者なし",
            "ファウルフライを 門脇 (三)が捕球してバッターアウト 1アウト"
          ]
        },
        {
          "number": "2：",
          "lines": [
            "8番 谷川原 健太 一死走者なし",
            "空振りの三振を喫する 2アウト"
          ]
        },
        {
          "number": "3：",
          "lines": [
            "9番 川瀬 晃 二死走者なし",
            "セカンドゴロ 3アウト"
          ]
        }
      ]
    },
    {
      "inning": "6回表",
      "detail": "巨人の攻撃",
      "plays": [
        {
          "number": "1：",
          "lines": [
            "3番 坂本 勇人 無死走者なし",
            "外角低めの球を打つもライトフライ 1アウト"
          ]
        },
        {
          "number": "2：",
          "lines": [
            "4番 ダルベック 一死走者なし",
            "外角低めのストレートを打つもライトフライ 2アウト"
          ]
        },
        {
          "number": "3：",
          "lines": [
            "5番 キャベッジ 二死走者なし",
            "ファーストゴロ 3アウト"
          ]
        }
      ]
    },
    {
      "inning": "6回裏",
      "detail": "ソフトバンクの攻撃",
      "plays": [
        {
          "number": "1：",
          "lines": [
            "1番 柳田 悠岐 無死走者なし",
            "低めの落ちる球を打つもライトフライ 1アウト"
          ]
        },
        {
          "number": "2：",
          "lines": [
            "2番 柳町 達 一死走者なし",
            "センターへのヒットで出塁 一塁"
          ]
        },
        {
          "number": "3：",
          "lines": [
            "3番 野村 勇 一死一塁",
            "一塁走者 柳町 →代走: イヒネ",
            "ソフトバンク・イヒネの二塁盗塁セーフの判定を巡り、巨人がリクエスト",
            "リプレー検証後判定変わらず",
            "一塁走者 イヒネ :盗塁成功 二塁",
            "ランナー二塁の2-2からセンターへのタイムリーヒット ソ 11-2 巨 一塁"
          ]
        },
        {
          "number": "4：",
          "lines": [
            "4番 山川 穂高 一死一塁",
            "外角低めの変化球を打つもライトフライ 2アウト"
          ]
        },
        {
          "number": "5：",
          "lines": [
            "5番 笹川 吉康 二死一塁",
            "センターへのヒットを放つ 一三塁"
          ]
        },
        {
          "number": "6：",
          "lines": [
            "6番 今宮 健太 二死一三塁",
            "ランナー一三塁の2-1からライトへのタイムリーヒット ソ 12-2 巨 一三塁"
          ]
        },
        {
          "number": "7：",
          "lines": [
            "7番 秋広 優人 二死一三塁",
            "2アウト一三塁の1-2からタイムリーヒット ソ 13-2 巨 一二塁"
          ]
        },
        {
          "number": "8：",
          "lines": [
            "代打 正木 智也 二死一二塁",
            "谷川原 →代打: 正木",
            "ショートフライ 3アウト"
          ]
        }
      ]
    },
    {
      "inning": "7回表",
      "detail": "巨人の攻撃",
      "plays": [
        {
          "number": "1：",
          "lines": [
            "6番 中山 礼都 無死走者なし",
            "投手交代: 伊藤 → オスナ 守備交代:キャッチャー 渡邉 守備変更: イヒネ →ライト　守備変更: 正木 →ファースト",
            "内角高めのストレートを打つもセンターフライ 1アウト"
          ]
        },
        {
          "number": "2：",
          "lines": [
            "7番 浦田 俊輔 一死走者なし",
            "ライトへのヒットを放つ 一塁"
          ]
        },
        {
          "number": "3：",
          "lines": [
            "代打 小林 誠司 一死一塁",
            "甲斐 →代打: 小林",
            "ライトへのヒットで出塁 一二塁"
          ]
        },
        {
          "number": "4：",
          "lines": [
            "9番 門脇 誠 一死一二塁",
            "1アウト一二塁からど真ん中のストレートを打つもライトフライ 2アウト一三塁"
          ]
        },
        {
          "number": "5：",
          "lines": [
            "1番 佐々木 俊輔 二死一三塁",
            "カウント0-2から空振り三振でバッターアウト 3アウト"
          ]
        }
      ]
    },
    {
      "inning": "7回裏",
      "detail": "ソフトバンクの攻撃",
      "plays": [
        {
          "number": "1：",
          "lines": [
            "9番 川瀬 晃 無死走者なし",
            "投手交代: 戸郷 → 田中瑛 守備交代:センター 宇都宮 守備変更: 小林 →キャッチャー",
            "フォアボールを選ぶ 一塁"
          ]
        },
        {
          "number": "2：",
          "lines": [
            "代打 井上 朋也 無死一塁",
            "柳田 →代打: 井上",
            "詰まった打球はセカンドゴロ 1アウト一塁"
          ]
        },
        {
          "number": "3：",
          "lines": [
            "2番 イヒネ イツア 一死一塁",
            "ストレートのフォアボールで出塁 一二塁"
          ]
        },
        {
          "number": "4：",
          "lines": [
            "3番 野村 勇 一死一二塁",
            "－巨人:内野手マウンドへ集まる－",
            "ランナー一二塁からライトへのヒット 満塁"
          ]
        },
        {
          "number": "5：",
          "lines": [
            "代打 オスーナ 一死満塁",
            "山川 →代打: オスーナ",
            "空振り三振でバッターアウト 2アウト"
          ]
        },
        {
          "number": "6：",
          "lines": [
            "5番 笹川 吉康 二死満塁",
            "セカンドゴロ 3アウト"
          ]
        }
      ]
    },
    {
      "inning": "8回表",
      "detail": "巨人の攻撃",
      "plays": [
        {
          "number": "1：",
          "lines": [
            "2番 泉口 友汰 無死走者なし",
            "投手交代: オスナ → 杉山 守備交代:ショート 庄子 守備変更: 井上 →ライト　守備変更: イヒネ ライト→レフト",
            "ライトへの二塁打 二塁"
          ]
        },
        {
          "number": "2：",
          "lines": [
            "代打 石塚 裕惺 無死二塁",
            "坂本勇 →代打: 石塚",
            "サードゴロ 1アウト"
          ]
        },
        {
          "number": "3：",
          "lines": [
            "4番 ダルベック 一死二塁",
            "空振り三振 2アウト"
          ]
        },
        {
          "number": "4：",
          "lines": [
            "5番 キャベッジ 二死二塁",
            "カウント2-2から空振り三振でバッターアウト 3アウト"
          ]
        }
      ]
    },
    {
      "inning": "8回裏",
      "detail": "ソフトバンクの攻撃",
      "plays": [
        {
          "number": "1：",
          "lines": [
            "6番 庄子 雄大 無死走者なし",
            "投手交代: 田中瑛 → 中川 守備交代:ライト 知念 守備交代:センター 皆川 守備変更: 宇都宮 センター→レフト　守備変更: 中山 ライト→ファースト",
            "フォアボールを選ぶ 一塁"
          ]
        },
        {
          "number": "2：",
          "lines": [
            "7番 渡邉 陸 無死一塁",
            "低めの変化球を打つもセンターフライ 1アウト"
          ]
        },
        {
          "number": "3：",
          "lines": [
            "8番 正木 智也 一死一塁",
            "7球粘るも内角低めの真っ直ぐに見逃し三振 2アウト"
          ]
        },
        {
          "number": "4：",
          "lines": [
            "代打 廣瀨 隆太 二死一塁",
            "川瀬 →代打: 廣瀨隆",
            "カウント1-0からレフトスタンドへの2ランホームラン ソ 15-2 巨"
          ]
        },
        {
          "number": "5：",
          "lines": [
            "1番 井上 朋也 二死走者なし",
            "内角高めの真っ直ぐを打つもセンターフライ 3アウト"
          ]
        }
      ]
    },
    {
      "inning": "9回表",
      "detail": "巨人の攻撃",
      "plays": [
        {
          "number": "1：",
          "lines": [
            "6番 中山 礼都 無死走者なし",
            "投手交代: 杉山 → 津森 守備変更: 廣瀨隆 →サード",
            "ショートゴロ 1アウト"
          ]
        },
        {
          "number": "2：",
          "lines": [
            "7番 浦田 俊輔 一死走者なし",
            "粘りを見せるも8球目を空振り、三振を喫する 2アウト"
          ]
        },
        {
          "number": "3：",
          "lines": [
            "8番 小林 誠司 二死走者なし",
            "ファウルフライを 渡邉 (捕)がつかんでバッターアウト 3アウト",
            "試合終了"
          ]
        }
      ]
    }
  ]
}