{
  "url": "https://www.nikkansports.com/baseball/professional/score/2025/cl2025090903.html",
  "scoreboard": [
    {
      "team": "ＤｅＮＡ",
      "R": "３"
    },
    {
      "team": "阪神",
      "R": "０"
    }
  ],
  "text_live": [
    {
      "inning": "試合前",
      "pregame": {
        "lineups": [
          {
            "team": "ＤｅＮＡ",
            "players": [
              "蝦名",
              "桑原",
              "筒香",
              "神里",
              "オースティン",
              "柴田",
              "佐野",
              "山本",
              "林"
            ]
          },
          {
            "team": "阪神",
            "players": [
              "近本",
              "中野",
              "森下",
              "佐藤輝",
              "大山",
              "木浪",
              "高寺",
              "坂本",
              "井坪"
            ]
          }
        ]
      }
    },
    {
      "inning": "1回表",
      "plays": [
        {
          "lines": [
            "1番 蝦名",
            "三振"
          ]
        }
      ]
    },
    {
      "inning": "2回表",
      "plays": [
        {
          "lines": [
            "1番 蝦名",
            "一飛"
          ]
        }
      ]
    },
    {
      "inning": "5回表",
      "plays": [
        {
          "lines": [
            "1番 蝦名",
            "右安"
          ]
        }
      ]
    },
    {
      "inning": "8回表",
      "plays": [
        {
          "lines": [
            "1番 蝦名",
            "右飛"
          ]
        }
      ]
    },
    {
      "inning": "1回表",
      "plays": [
        {
          "lines": [
            "2番 桑原",
            "三振"
          ]
        }
      ]
    },
    {
      "inning": "3回表",
      "plays": [
        {
          "lines": [
            "2番 桑原",
            "投ゴ"
          ]
        }
      ]
    },
    {
      "inning": "5回表",
      "plays": [
        {
          "lines": [
            "2番 桑原",
            "二飛"
          ]
        }
      ]
    },
    {
      "inning": "8回表",
      "plays": [
        {
          "lines": [
            "2番 桑原",
            "右飛"
          ]
        }
      ]
    },
    {
      "inning": "1回表",
      "plays": [
        {
          "lines": [
            "3番 筒香",
            "右飛"
          ]
        }
      ]
    },
    {
      "inning": "3回表",
      "plays": [
        {
          "lines": [
            "3番 筒香",
            "二ゴ"
          ]
        }
      ]
    },
    {
      "inning": "6回表",
      "plays": [
        {
          "lines": [
            "3番 筒香",
            "中飛"
          ]
        }
      ]
    },
    {
      "inning": "9回表",
      "plays": [
        {
          "lines": [
            "3番 筒香",
            "中飛"
          ]
        }
      ]
    },
    {
      "inning": "2回表",
      "plays": [
        {
          "lines": [
            "5番 オースティン",
            "左２"
          ]
        }
      ]
    },
    {
      "inning": "3回表",
      "plays": [
        {
          "lines": [
            "5番 オースティン",
            "三振"
          ]
        }
      ]
    },
    {
      "inning": "6回表",
      "plays": [
        {
          "lines": [
            "5番 オースティン",
            "中飛"
          ]
        }
      ]
    },
    {
      "inning": "9回表",
      "plays": [
        {
          "lines": [
            "5番 オースティン",
            "右飛"
          ]
        }
      ]
    },
    {
      "inning": "2回表",
      "plays": [
        {
          "lines": [
            "7番 佐野",
            "右２"
          ]
        }
      ]
    },
    {
      "inning": "4回表",
      "plays": [
        {
          "lines": [
            "7番 佐野",
            "二ゴ"
          ]
        }
      ]
    },
    {
      "inning": "6回表",
      "plays": [
        {
          "lines": [
            "7番 佐野",
            "三振"
          ]
        }
      ]
    },
    {
      "inning": "9回表",
      "plays": [
        {
          "lines": [
            "7番 佐野",
            "二ゴ"
          ]
        }
      ]
    },
    {
      "inning": "2回表",
      "plays": [
        {
          "lines": [
            "8番 山本",
            "右飛"
          ]
        }
      ]
    },
    {
      "inning": "4回表",
      "plays": [
        {
          "lines": [
            "8番 山本",
            "投ゴ"
          ]
        }
      ]
    },
    {
      "inning": "7回表",
      "plays": [
        {
          "lines": [
            "8番 山本",
            "二ゴ"
          ]
        }
      ]
    },
    {
      "inning": "2回表",
      "plays": [
        {
          "lines": [
            "9番 林",
            "右飛"
          ]
        }
      ]
    },
    {
      "inning": "4回表",
      "plays": [
        {
          "lines": [
            "9番 林",
            "三振"
          ]
        }
      ]
    },
    {
      "inning": "7回表",
      "plays": [
        {
          "lines": [
            "9番 林",
            "三振"
          ]
        }
      ]
    },
    {
      "inning": "2回表",
      "plays": [
        {
          "lines": [
            "9番 京田",
            "敬遠"
          ]
        }
      ]
    },
    {
      "inning": "5回表",
      "plays": [
        {
          "lines": [
            "9番 京田",
            "中飛"
          ]
        }
      ]
    },
    {
      "inning": "7回表",
      "plays": [
        {
          "lines": [
            "9番 京田",
            "三振"
          ]
        }
      ]
    },
    {
      "inning": "2回表",
      "plays": [
        {
          "lines": [
            "9番 ケイ",
            "左２"
          ]
        }
      ]
    },
    {
      "inning": "5回表",
      "plays": [
        {
          "lines": [
            "9番 ケイ",
            "左飛"
          ]
        }
      ]
    },
    {
      "inning": "8回表",
      "plays": [
        {
          "lines": [
            "9番 ビシエド",
            "三ゴ"
          ]
        }
      ]
    },
    {
      "inning": "1回裏",
      "plays": [
        {
          "lines": [
            "1番 近本",
            "左安"
          ]
        }
      ]
    },
    {
      "inning": "3回裏",
      "plays": [
        {
          "lines": [
            "1番 近本",
            "投ゴ"
          ]
        }
      ]
    },
    {
      "inning": "6回裏",
      "plays": [
        {
          "lines": [
            "1番 近本",
            "二ゴ"
          ]
        }
      ]
    },
    {
      "inning": "9回裏",
      "plays": [
        {
          "lines": [
            "1番 近本",
            "投安"
          ]
        }
      ]
    },
    {
      "inning": "1回裏",
      "plays": [
        {
          "lines": [
            "2番 中野",
            "中飛"
          ]
        }
      ]
    },
    {
      "inning": "4回裏",
      "plays": [
        {
          "lines": [
            "2番 中野",
            "三振"
          ]
        }
      ]
    },
    {
      "inning": "6回裏",
      "plays": [
        {
          "lines": [
            "2番 中野",
            "左安"
          ]
        }
      ]
    },
    {
      "inning": "9回裏",
      "plays": [
        {
          "lines": [
            "2番 中野",
            "三ゴ"
          ]
        }
      ]
    },
    {
      "inning": "1回裏",
      "plays": [
        {
          "lines": [
            "3番 森下",
            "三失"
          ]
        }
      ]
    },
    {
      "inning": "4回裏",
      "plays": [
        {
          "lines": [
            "3番 森下",
            "中飛"
          ]
        }
      ]
    },
    {
      "inning": "6回裏",
      "plays": [
        {
          "lines": [
            "3番 森下",
            "遊ゴ"
          ]
        }
      ]
    },
    {
      "inning": "9回裏",
      "plays": [
        {
          "lines": [
            "3番 森下",
            "左安"
          ]
        }
      ]
    },
    {
      "inning": "1回裏",
      "plays": [
        {
          "lines": [
            "4番 佐藤輝",
            "三振"
          ]
        }
      ]
    },
    {
      "inning": "4回裏",
      "plays": [
        {
          "lines": [
            "4番 佐藤輝",
            "一ゴ"
          ]
        }
      ]
    },
    {
      "inning": "7回裏",
      "plays": [
        {
          "lines": [
            "4番 佐藤輝",
            "三邪"
          ]
        }
      ]
    },
    {
      "inning": "9回裏",
      "plays": [
        {
          "lines": [
            "4番 佐藤輝",
            "三振"
          ]
        }
      ]
    },
    {
      "inning": "2回裏",
      "plays": [
        {
          "lines": [
            "5番 大山",
            "遊ゴ"
          ]
        }
      ]
    },
    {
      "inning": "5回裏",
      "plays": [
        {
          "lines": [
            "5番 大山",
            "右飛"
          ]
        }
      ]
    },
    {
      "inning": "7回裏",
      "plays": [
        {
          "lines": [
            "5番 大山",
            "三振"
          ]
        }
      ]
    },
    {
      "inning": "9回裏",
      "plays": [
        {
          "lines": [
            "5番 大山",
            "三振"
          ]
        }
      ]
    },
    {
      "inning": "2回裏",
      "plays": [
        {
          "lines": [
            "6番 木浪",
            "二ゴ"
          ]
        }
      ]
    },
    {
      "inning": "5回裏",
      "plays": [
        {
          "lines": [
            "6番 木浪",
            "二ゴ"
          ]
        }
      ]
    },
    {
      "inning": "7回裏",
      "plays": [
        {
          "lines": [
            "6番 木浪",
            "右飛"
          ]
        }
      ]
    },
    {
      "inning": "2回裏",
      "plays": [
        {
          "lines": [
            "7番 高寺",
            "三振"
          ]
        }
      ]
    },
    {
      "inning": "5回裏",
      "plays": [
        {
          "lines": [
            "7番 高寺",
            "左安"
          ]
        }
      ]
    },
    {
      "inning": "8回裏",
      "plays": [
        {
          "lines": [
            "7番 高寺",
            "三振"
          ]
        }
      ]
    },
    {
      "inning": "3回裏",
      "plays": [
        {
          "lines": [
            "8番 坂本",
            "三振"
          ]
        }
      ]
    },
    {
      "inning": "5回裏",
      "plays": [
        {
          "lines": [
            "8番 坂本",
            "二邪"
          ]
        }
      ]
    },
    {
      "inning": "8回裏",
      "plays": [
        {
          "lines": [
            "9番 井坪",
            "三ゴ"
          ]
        }
      ]
    },
    {
      "inning": "3回裏",
      "plays": [
        {
          "lines": [
            "9番 村上",
            "三振"
          ]
        }
      ]
    },
    {
      "inning": "6回裏",
      "plays": [
        {
          "lines": [
            "9番 村上",
            "三振"
          ]
        }
      ]
    },
    {
      "inning": "8回裏",
      "plays": [
        {
          "lines": [
            "9番 豊田",
            "三振"
          ]
        }
      ]
    }
  ]
}