{
  "url": "https://www.nikkansports.com/baseball/professional/score/2025/pl2025070204.html",
  "scoreboard": [
    {
      "team": "ロッテ",
      "R": "６"
    },
    {
      "team": "楽天",
      "R": "３"
    }
  ],
  "text_live": [
    {
      "inning": "試合前",
      "pregame": {
        "lineups": [
          {
            "team": "ロッテ",
            "players": [
              "藤原",
              "寺地",
              "安田",
              "山本",
              "西川",
              "ソト",
              "茶谷",
              "藤岡",
              "友杉"
            ]
          },
          {
            "team": "楽天",
            "players": [
              "辰己",
              "村林",
              "黒川",
              "ゴンザレス",
              "渡辺佳",
              "ボイト",
              "小深田",
              "中島",
              "宗山"
            ]
          }
        ]
      }
    },
    {
      "inning": "1回表",
      "plays": [
        {
          "lines": [
            "1番 藤原",
            "三邪"
          ]
        }
      ]
    },
    {
      "inning": "3回表",
      "plays": [
        {
          "lines": [
            "1番 藤原",
            "中飛"
          ]
        }
      ]
    },
    {
      "inning": "5回表",
      "plays": [
        {
          "lines": [
            "1番 藤原",
            "投ゴ"
          ]
        }
      ]
    },
    {
      "inning": "6回表",
      "plays": [
        {
          "lines": [
            "1番 藤原",
            "中安"
          ]
        }
      ]
    },
    {
      "inning": "9回表",
      "plays": [
        {
          "lines": [
            "1番 藤原",
            "二ゴ"
          ]
        }
      ]
    },
    {
      "inning": "1回表",
      "plays": [
        {
          "lines": [
            "2番 寺地",
            "中２"
          ]
        }
      ]
    },
    {
      "inning": "3回表",
      "plays": [
        {
          "lines": [
            "2番 寺地",
            "中安"
          ]
        }
      ]
    },
    {
      "inning": "6回表",
      "plays": [
        {
          "lines": [
            "2番 寺地",
            "投安"
          ]
        }
      ]
    },
    {
      "inning": "7回表",
      "plays": [
        {
          "lines": [
            "2番 寺地",
            "投ゴ"
          ]
        }
      ]
    },
    {
      "inning": "10回表",
      "plays": [
        {
          "lines": [
            "2番 寺地",
            "投ゴ"
          ]
        }
      ]
    },
    {
      "inning": "1回表",
      "plays": [
        {
          "lines": [
            "3番 安田",
            "三振"
          ]
        }
      ]
    },
    {
      "inning": "3回表",
      "plays": [
        {
          "lines": [
            "3番 安田",
            "三振"
          ]
        }
      ]
    },
    {
      "inning": "6回表",
      "plays": [
        {
          "lines": [
            "3番 安田",
            "左安"
          ]
        }
      ]
    },
    {
      "inning": "8回表",
      "plays": [
        {
          "lines": [
            "3番 安田",
            "右安"
          ]
        }
      ]
    },
    {
      "inning": "10回表",
      "plays": [
        {
          "lines": [
            "3番 安田",
            "三振"
          ]
        }
      ]
    },
    {
      "inning": "1回表",
      "plays": [
        {
          "lines": [
            "4番 山本",
            "三ゴ"
          ]
        }
      ]
    },
    {
      "inning": "4回表",
      "plays": [
        {
          "lines": [
            "4番 山本",
            "三振"
          ]
        }
      ]
    },
    {
      "inning": "6回表",
      "plays": [
        {
          "lines": [
            "4番 山本",
            "左安"
          ]
        }
      ]
    },
    {
      "inning": "8回表",
      "plays": [
        {
          "lines": [
            "4番 山本",
            "遊飛"
          ]
        }
      ]
    },
    {
      "inning": "10回表",
      "plays": [
        {
          "lines": [
            "4番 山本",
            "二ゴ"
          ]
        }
      ]
    },
    {
      "inning": "2回表",
      "plays": [
        {
          "lines": [
            "5番 西川",
            "投ゴ"
          ]
        }
      ]
    },
    {
      "inning": "4回表",
      "plays": [
        {
          "lines": [
            "5番 西川",
            "死球"
          ]
        }
      ]
    },
    {
      "inning": "6回表",
      "plays": [
        {
          "lines": [
            "5番 西川",
            "左安"
          ]
        }
      ]
    },
    {
      "inning": "8回表",
      "plays": [
        {
          "lines": [
            "5番 西川",
            "三振"
          ]
        }
      ]
    },
    {
      "inning": "2回表",
      "plays": [
        {
          "lines": [
            "6番 ソト",
            "左飛"
          ]
        }
      ]
    },
    {
      "inning": "4回表",
      "plays": [
        {
          "lines": [
            "6番 ソト",
            "三飛"
          ]
        }
      ]
    },
    {
      "inning": "6回表",
      "plays": [
        {
          "lines": [
            "6番 ソト",
            "左安"
          ]
        }
      ]
    },
    {
      "inning": "8回表",
      "plays": [
        {
          "lines": [
            "6番 ソト",
            "三振"
          ]
        }
      ]
    },
    {
      "inning": "2回表",
      "plays": [
        {
          "lines": [
            "8番 藤岡",
            "遊ゴ"
          ]
        }
      ]
    },
    {
      "inning": "4回表",
      "plays": [
        {
          "lines": [
            "8番 藤岡",
            "左飛"
          ]
        }
      ]
    },
    {
      "inning": "6回表",
      "plays": [
        {
          "lines": [
            "8番 藤岡",
            "左２"
          ]
        }
      ]
    },
    {
      "inning": "9回表",
      "plays": [
        {
          "lines": [
            "8番 藤岡",
            "四球"
          ]
        }
      ]
    },
    {
      "inning": "3回表",
      "plays": [
        {
          "lines": [
            "9番 友杉",
            "左安"
          ]
        }
      ]
    },
    {
      "inning": "5回表",
      "plays": [
        {
          "lines": [
            "9番 友杉",
            "右飛"
          ]
        }
      ]
    },
    {
      "inning": "6回表",
      "plays": [
        {
          "lines": [
            "9番 友杉",
            "投ギ"
          ]
        }
      ]
    },
    {
      "inning": "9回表",
      "plays": [
        {
          "lines": [
            "9番 友杉",
            "投ギ"
          ]
        }
      ]
    },
    {
      "inning": "3回表",
      "plays": [
        {
          "lines": [
            "9番 高部",
            "三振"
          ]
        }
      ]
    },
    {
      "inning": "5回表",
      "plays": [
        {
          "lines": [
            "9番 高部",
            "二ゴ"
          ]
        }
      ]
    },
    {
      "inning": "6回表",
      "plays": [
        {
          "lines": [
            "9番 高部",
            "左飛"
          ]
        }
      ]
    },
    {
      "inning": "9回表",
      "plays": [
        {
          "lines": [
            "9番 高部",
            "中飛"
          ]
        }
      ]
    },
    {
      "inning": "1回裏",
      "plays": [
        {
          "lines": [
            "1番 辰己",
            "二ゴ"
          ]
        }
      ]
    },
    {
      "inning": "3回裏",
      "plays": [
        {
          "lines": [
            "1番 辰己",
            "中犠"
          ]
        }
      ]
    },
    {
      "inning": "6回裏",
      "plays": [
        {
          "lines": [
            "1番 辰己",
            "左飛"
          ]
        }
      ]
    },
    {
      "inning": "8回裏",
      "plays": [
        {
          "lines": [
            "1番 辰己",
            "左安"
          ]
        }
      ]
    },
    {
      "inning": "1回裏",
      "plays": [
        {
          "lines": [
            "2番 村林",
            "二ゴ"
          ]
        }
      ]
    },
    {
      "inning": "3回裏",
      "plays": [
        {
          "lines": [
            "2番 村林",
            "三振"
          ]
        }
      ]
    },
    {
      "inning": "6回裏",
      "plays": [
        {
          "lines": [
            "2番 村林",
            "二安"
          ]
        }
      ]
    },
    {
      "inning": "8回裏",
      "plays": [
        {
          "lines": [
            "2番 村林",
            "左安"
          ]
        }
      ]
    },
    {
      "inning": "1回裏",
      "plays": [
        {
          "lines": [
            "3番 黒川",
            "三飛"
          ]
        }
      ]
    },
    {
      "inning": "4回裏",
      "plays": [
        {
          "lines": [
            "3番 黒川",
            "二飛"
          ]
        }
      ]
    },
    {
      "inning": "6回裏",
      "plays": [
        {
          "lines": [
            "3番 黒川",
            "三ゴ"
          ]
        }
      ]
    },
    {
      "inning": "8回裏",
      "plays": [
        {
          "lines": [
            "3番 黒川",
            "左飛"
          ]
        }
      ]
    },
    {
      "inning": "2回裏",
      "plays": [
        {
          "lines": [
            "4番 ゴンザレス",
            "一ゴ"
          ]
        }
      ]
    },
    {
      "inning": "4回裏",
      "plays": [
        {
          "lines": [
            "4番 ゴンザレス",
            "右安"
          ]
        }
      ]
    },
    {
      "inning": "7回裏",
      "plays": [
        {
          "lines": [
            "4番 ゴンザレス",
            "左飛"
          ]
        }
      ]
    },
    {
      "inning": "8回裏",
      "plays": [
        {
          "lines": [
            "4番 ゴンザレス",
            "遊併"
          ]
        }
      ]
    },
    {
      "inning": "2回裏",
      "plays": [
        {
          "lines": [
            "5番 渡辺佳",
            "遊直"
          ]
        }
      ]
    },
    {
      "inning": "4回裏",
      "plays": [
        {
          "lines": [
            "5番 渡辺佳",
            "二直"
          ]
        }
      ]
    },
    {
      "inning": "7回裏",
      "plays": [
        {
          "lines": [
            "5番 渡辺佳",
            "四球"
          ]
        }
      ]
    },
    {
      "inning": "9回裏",
      "plays": [
        {
          "lines": [
            "5番 渡辺佳",
            "三振"
          ]
        }
      ]
    },
    {
      "inning": "2回裏",
      "plays": [
        {
          "lines": [
            "6番 ボイト",
            "三振"
          ]
        }
      ]
    },
    {
      "inning": "5回裏",
      "plays": [
        {
          "lines": [
            "6番 ボイト",
            "左安"
          ]
        }
      ]
    },
    {
      "inning": "7回裏",
      "plays": [
        {
          "lines": [
            "6番 ボイト",
            "左本"
          ]
        }
      ]
    },
    {
      "inning": "9回裏",
      "plays": [
        {
          "lines": [
            "6番 ボイト",
            "右安"
          ]
        }
      ]
    },
    {
      "inning": "3回裏",
      "plays": [
        {
          "lines": [
            "8番 中島",
            "四球"
          ]
        }
      ]
    },
    {
      "inning": "5回裏",
      "plays": [
        {
          "lines": [
            "8番 中島",
            "二ゴ"
          ]
        }
      ]
    },
    {
      "inning": "7回裏",
      "plays": [
        {
          "lines": [
            "8番 中島",
            "三振"
          ]
        }
      ]
    },
    {
      "inning": "9回裏",
      "plays": [
        {
          "lines": [
            "8番 中島",
            "三振"
          ]
        }
      ]
    },
    {
      "inning": "3回裏",
      "plays": [
        {
          "lines": [
            "9番 宗山",
            "一安"
          ]
        }
      ]
    },
    {
      "inning": "5回裏",
      "plays": [
        {
          "lines": [
            "9番 宗山",
            "中飛"
          ]
        }
      ]
    },
    {
      "inning": "7回裏",
      "plays": [
        {
          "lines": [
            "9番 宗山",
            "右安"
          ]
        }
      ]
    },
    {
      "inning": "9回裏",
      "plays": [
        {
          "lines": [
            "9番 宗山",
            "四球"
          ]
        }
      ]
    },
    {
      "inning": "3回裏",
      "plays": [
        {
          "lines": [
            "9番 石原",
            "捕ギ"
          ]
        }
      ]
    },
    {
      "inning": "6回裏",
      "plays": [
        {
          "lines": [
            "9番 堀内",
            "三振"
          ]
        }
      ]
    },
    {
      "inning": "7回裏",
      "plays": [
        {
          "lines": [
            "9番 堀内",
            "中飛"
          ]
        }
      ]
    },
    {
      "inning": "9回裏",
      "plays": [
        {
          "lines": [
            "9番 浅村",
            "三振"
          ]
        }
      ]
    }
  ]
}